genx/__init__.py
genx/_version.py
genx/react_jupyter_widget.py
genx/static/extension.js
genx/static/index.js
genx/static/index.js.map
genx_widget-0.1.1b1.data/data/etc/jupyter/nbconfig/notebook.d/genx-widget.json
genx_widget-0.1.1b1.data/data/share/jupyter/nbextensions/genx-widget/extension.js
genx_widget-0.1.1b1.data/data/share/jupyter/nbextensions/genx-widget/index.js
genx_widget-0.1.1b1.data/data/share/jupyter/nbextensions/genx-widget/index.js.map
genx_widget-0.1.1b1.dist-info/METADATA
genx_widget-0.1.1b1.dist-info/WHEEL
genx_widget-0.1.1b1.dist-info/top_level.txt
genx_widget-0.1.1b1.dist-info/RECORD
